LICENSE.txt
MANIFEST.in
README.rst
setup.py
django_facebook_comments.egg-info/PKG-INFO
django_facebook_comments.egg-info/SOURCES.txt
django_facebook_comments.egg-info/dependency_links.txt
django_facebook_comments.egg-info/not-zip-safe
django_facebook_comments.egg-info/top_level.txt
facebook_comments/__init__.py
facebook_comments/models.py
facebook_comments/tests.py
facebook_comments/urls.py
facebook_comments/views.py
facebook_comments/conf/__init__.py
facebook_comments/conf/settings.py
facebook_comments/templates/facebook_comments/cached_comments.html
facebook_comments/templates/facebook_comments/channel.html
facebook_comments/templates/facebook_comments/comment_box.html
facebook_comments/templatetags/__init__.py
facebook_comments/templatetags/fb_cached_comments.py
facebook_comments/templatetags/fb_comments.py