Metadata-Version: 1.1
Name: django-facebook-comments
Version: 0.1.5
Summary: Drop-in facebook comments for django
Home-page: https://bitbucket.org/sirpengi/django-facebook-comments
Author: Shu Zong Chen
Author-email: shu.chen@freelancedreams.com
License: MIT License
Download-URL: https://bitbucket.org/sirpengi/django-facebook-comments/downloads
Keywords: django facebook comments templatetag
Platform: any
Classifier: Development Status :: 5 - Production/Stable
Classifier: Environment :: Web Environment
Classifier: Framework :: Django
Classifier: Intended Audience :: Developers
Classifier: License :: OSI Approved :: MIT License
Classifier: Operating System :: OS Independent
Classifier: Programming Language :: Python
Classifier: Topic :: Software Development :: Libraries :: Application Frameworks
Classifier: Topic :: Software Development :: Libraries :: Python Modules
